flaskapiRequest/__init__.py
flaskapiRequest/api_request/__init__.py
flaskapiRequest/api_request/requests_module.py
flaskapiRequest/configurations/__init__.py
flaskapiRequest/configurations/context.py
flaskapiRequest/configurations/fileReader.py
flaskapiRequest/configurations/helpers.py
flaskapiRequest-0.0.1.dist-info/METADATA
flaskapiRequest-0.0.1.dist-info/WHEEL
flaskapiRequest-0.0.1.dist-info/top_level.txt
flaskapiRequest-0.0.1.dist-info/RECORD
